odoo8_addon_hr_employee_gravatar-8.0.1.0.0.99.dev18-py2.7-nspkg.pth
odoo8_addon_hr_employee_gravatar-8.0.1.0.0.99.dev18.dist-info/DESCRIPTION.rst
odoo8_addon_hr_employee_gravatar-8.0.1.0.0.99.dev18.dist-info/METADATA
odoo8_addon_hr_employee_gravatar-8.0.1.0.0.99.dev18.dist-info/RECORD
odoo8_addon_hr_employee_gravatar-8.0.1.0.0.99.dev18.dist-info/WHEEL
odoo8_addon_hr_employee_gravatar-8.0.1.0.0.99.dev18.dist-info/metadata.json
odoo8_addon_hr_employee_gravatar-8.0.1.0.0.99.dev18.dist-info/namespace_packages.txt
odoo8_addon_hr_employee_gravatar-8.0.1.0.0.99.dev18.dist-info/top_level.txt
odoo_addons/hr_employee_gravatar/README.rst
odoo_addons/hr_employee_gravatar/__init__.py
odoo_addons/hr_employee_gravatar/__openerp__.py
odoo_addons/hr_employee_gravatar/i18n/ar.po
odoo_addons/hr_employee_gravatar/i18n/ca.po
odoo_addons/hr_employee_gravatar/i18n/da.po
odoo_addons/hr_employee_gravatar/i18n/de.po
odoo_addons/hr_employee_gravatar/i18n/el_GR.po
odoo_addons/hr_employee_gravatar/i18n/es.po
odoo_addons/hr_employee_gravatar/i18n/es_ES.po
odoo_addons/hr_employee_gravatar/i18n/fi.po
odoo_addons/hr_employee_gravatar/i18n/fr.po
odoo_addons/hr_employee_gravatar/i18n/fr_CH.po
odoo_addons/hr_employee_gravatar/i18n/hr.po
odoo_addons/hr_employee_gravatar/i18n/hr_HR.po
odoo_addons/hr_employee_gravatar/i18n/hr_employee_gravatar.pot
odoo_addons/hr_employee_gravatar/i18n/it.po
odoo_addons/hr_employee_gravatar/i18n/nl.po
odoo_addons/hr_employee_gravatar/i18n/pt_BR.po
odoo_addons/hr_employee_gravatar/i18n/sl.po
odoo_addons/hr_employee_gravatar/i18n/tr.po
odoo_addons/hr_employee_gravatar/i18n/tr_TR.po
odoo_addons/hr_employee_gravatar/i18n/zh_CN.po
odoo_addons/hr_employee_gravatar/models/__init__.py
odoo_addons/hr_employee_gravatar/models/res_users.py
odoo_addons/hr_employee_gravatar/static/description/icon.png
